{
  "0": "",
  "1": "act_common",
  "2": "act_kiryu",
  "3": "adventure_common",
  "4": "adv_caba_drinking_party",
  "5": "amb",
  "6": "amb_osaka",
  "7": "battle_common",
  "8": "bbg_a",
  "9": "bbg_bgm_fukuda",
  "10": "bbg_bgm_shoji",
  "11": "bbg_bgm_yoshida",
  "12": "bbg_f",
  "13": "bbg_s",
  "14": "bbg_y",
  "15": "bgm_cont_test",
  "16": "caba_bgm",
  "17": "caba_operation",
  "18": "clan_uv_akiyama",
  "19": "clan_uv_amon",
  "20": "clan_uv_daigo",
  "21": "clan_uv_date",
  "22": "clan_uv_joe",
  "23": "clan_uv_kiryu",
  "24": "clan_uv_kojima",
  "25": "clan_uv_majima",
  "26": "clan_uv_masao",
  "27": "clan_uv_master",
  "28": "clan_uv_naitou",
  "29": "clan_uv_okada",
  "30": "clan_uv_pokecir",
  "31": "clan_uv_saejima",
  "32": "clan_uv_sodachi",
  "33": "clan_uv_tanahashi",
  "34": "clan_uv_tenzan",
  "35": "clan_uv_yano",
  "36": "Generic",
  "37": "down_l_default",
  "38": "down_m_default",
  "39": "down_s_default",
  "40": "efx_common",
  "41": "guard_bokuto",
  "42": "guard_default",
  "43": "guard_katana",
  "44": "guard_metal",
  "45": "guard_sude",
  "46": "gv_mng_caba_caba01",
  "47": "gv_mng_caba_caba02",
  "48": "gv_mng_caba_caba03",
  "49": "gv_mng_caba_caba04",
  "50": "gv_mng_caba_caba05",
  "51": "gv_mng_caba_caba06",
  "52": "gv_mng_caba_customer01",
  "53": "gv_mng_caba_customer02",
  "54": "gv_mng_caba_customer03",
  "55": "gv_mng_caba_customer04",
  "56": "gv_mng_caba_customer05",
  "57": "gv_mng_caba_customer06",
  "58": "gv_mng_golf_kiryu",
  "59": "kaiwabgm",
  "60": "kaiwabgm_taiken",
  "61": "menu_cil_cmn",
  "62": "menu_default",
  "63": "menu_shop_cmn",
  "64": "menu_title",
  "65": "message",
  "66": "minig_batting",
  "67": "minig_batting_kiryu",
  "68": "minig_bj",
  "69": "minig_clan_se",
  "70": "minig_clan_vo_kiryu",
  "71": "minig_darts_kiryu",
  "72": "minig_darts_rival02",
  "73": "minig_darts_rival03",
  "74": "minig_darts_se",
  "75": "minig_golf",
  "76": "minig_karaoke_ainote_3shine",
  "77": "minig_karaoke_ainote_butterfly",
  "78": "minig_karaoke_ainote_hanyo",
  "79": "minig_karaoke_ainote_otometal",
  "80": "minig_karaoke_ainote_ring",
  "81": "minig_karaoke_bgm",
  "82": "minig_karaoke_cmn",
  "83": "minig_koikoi",
  "84": "minig_mj_f20a",
  "85": "minig_mj_f20b",
  "86": "minig_mj_f40",
  "87": "minig_mj_fsp",
  "88": "minig_mj_kindai_pl_01",
  "89": "minig_mj_kindai_pl_02",
  "90": "minig_mj_kindai_pl_03",
  "91": "minig_mj_kindai_pl_04",
  "92": "minig_mj_kindai_pl_05",
  "93": "minig_mj_kindai_pl_06",
  "94": "minig_mj_kindai_pl_07",
  "95": "minig_mj_kindai_pl_08",
  "96": "minig_mj_kindai_pl_09",
  "97": "minig_mj_kiryu",
  "98": "minig_mj_m20a",
  "99": "minig_mj_m20b",
  "100": "minig_mj_m30a",
  "101": "minig_mj_m30b",
  "102": "minig_mj_m40",
  "103": "minig_mj_majima",
  "104": "minig_mj_mk1a",
  "105": "minig_mj_mk4r",
  "106": "minig_mj_mk5n",
  "107": "minig_mj_msp",
  "108": "minig_mj_osk_f_obasan01",
  "109": "minig_mj_osk_f_sexy01",
  "110": "minig_mj_osk_m_ippan30s",
  "111": "minig_mj_osk_m_yakuza40s",
  "112": "minig_mj_osk_m_young_l",
  "113": "minig_mj_se",
  "114": "minig_oicho",
  "115": "minig_poker",
  "116": "minig_prize",
  "117": "minig_shogi",
  "118": "mngbgm_clan",
  "119": "otherbgm",
  "120": "proto_bgm",
  "121": "sys_se_gameover",
  "122": "talk_dammy_cmn",
  "123": "testrom_kaiwa_bgm",
  "124": "usen",
  "125": "vehicle_cmn",
  "126": "arm_alpsdoor",
  "127": "arm_amondrone",
  "128": "arm_amonrumba",
  "129": "arm_bathdoor",
  "130": "arm_bicycle",
  "131": "arm_bigkanban",
  "132": "arm_bike",
  "133": "arm_bokuto",
  "134": "arm_bomb",
  "135": "arm_breakbin",
  "136": "arm_breakshelf",
  "137": "arm_buranko",
  "138": "arm_can",
  "139": "arm_cardboard",
  "140": "arm_cardbordshelf",
  "141": "arm_chopstick",
  "142": "arm_clangun",
  "143": "arm_crashshelf",
  "144": "arm_default",
  "145": "arm_dish",
  "146": "arm_dosu",
  "147": "arm_doubledoor",
  "148": "arm_drumexp",
  "149": "arm_drumkan",
  "150": "arm_ev",
  "151": "arm_flour",
  "152": "arm_fusuma",
  "153": "arm_fuzokuswg",
  "154": "arm_garbage",
  "155": "arm_glass",
  "156": "arm_glass_cracks",
  "157": "arm_gun",
  "158": "arm_haizaraglass",
  "159": "arm_hammer",
  "160": "arm_hardball",
  "161": "arm_hirosedoor",
  "162": "arm_karistick",
  "163": "arm_katana",
  "164": "arm_kiyomidoor",
  "165": "arm_machinegun",
  "166": "arm_meet",
  "167": "arm_meriken",
  "168": "arm_metalbat",
  "169": "arm_metalchair",
  "170": "arm_metaldoubledoor",
  "171": "arm_metalkomono",
  "172": "arm_metalpot",
  "173": "arm_metalslidedoor",
  "174": "arm_metal_harddoor",
  "175": "arm_morenodoor",
  "176": "arm_oldev",
  "177": "arm_paper",
  "178": "arm_pipe",
  "179": "arm_plant",
  "180": "arm_propan",
  "181": "arm_pylon",
  "182": "arm_rope",
  "183": "arm_rpg",
  "184": "arm_serenadoor",
  "185": "arm_shelf",
  "186": "arm_shelfkan",
  "187": "arm_shoukaki",
  "188": "arm_silent",
  "189": "arm_siren",
  "190": "arm_slidedoor",
  "191": "arm_soccer",
  "192": "arm_sofa",
  "193": "arm_spray",
  "194": "arm_steelkanban",
  "195": "arm_stonegareki",
  "196": "arm_suigundoor",
  "197": "arm_tablestone",
  "198": "arm_testautodoor",
  "199": "arm_testbin",
  "200": "arm_testchair",
  "201": "arm_testdesk",
  "202": "arm_testdoor",
  "203": "arm_testtone",
  "204": "arm_tonfa",
  "205": "arm_turimeet",
  "206": "arm_vendhing",
  "207": "arm_woodbat",
  "208": "arm_wooddoor",
  "209": "arm_woodgareki",
  "210": "arm_woodkomono",
  "211": "arm_yari",
  "212": "arm_zousendoor",
  "213": "arm_zousendouble",
  "214": "arm_zousenheavy",
  "215": "auth_a01_0010_walk_through_disco",
  "216": "auth_a01_0010_walk_through_disco_a",
  "217": "auth_a01_0012_walk_through_disco_b",
  "218": "auth_a01_0013_old_building_memory",
  "219": "auth_a01_0015_old_building_baby",
  "220": "auth_a01_0020_yuuya_knockout_chinese",
  "221": "auth_a01_0030_kiryu_room",
  "222": "auth_a01_0040_terada_shoot_by_oumi",
  "223": "auth_a01_0080_kiryu_meet_daigo",
  "224": "auth_a01_0105_battle_with_daigo",
  "225": "auth_a02_0030_battle_with_ryuuji_tesita",
  "226": "auth_a02_0040_talk_with_ryuuji",
  "227": "auth_a03_0010_sayama_in_kawano_office",
  "228": "auth_a03_0050_ryuuji_intrusion",
  "229": "auth_a03_0080_knockdown_ryuuji",
  "230": "auth_a03_0090_kiryu_arrested_by_sayama",
  "231": "auth_a04_0030_sayama_shoot_by_someone",
  "232": "auth_a04_0090_fight_with_ezaki",
  "233": "auth_a04_0100_knockdown_ezaki",
  "234": "auth_a05_0010_sayama_down",
  "235": "auth_a05_0020_bring_sayama_to_serena",
  "236": "auth_a05_0040_talk_with_sayama",
  "237": "auth_a05_0110_fight_with_majima",
  "238": "auth_a05_0140_kiryu_talk_old_days",
  "239": "auth_a06_0020_date_talk_info_to_kazuki",
  "240": "auth_a06_0030_four_men_gunfight",
  "241": "auth_a07_0010_emergency_patient",
  "242": "auth_a07_0050_fight_with_kim_and_yong",
  "243": "auth_a07_0060_knock_down_kim_and_yong",
  "244": "auth_a07_0075_ir_sung_ha_info",
  "245": "auth_a08_0130_sayama_typing",
  "246": "auth_a09_0020_doujima_talk",
  "247": "auth_a09_0060_ryuji_arrival",
  "248": "auth_a09_0090_majima_talk",
  "249": "auth_a09_0140_fitht_with_shindo",
  "250": "auth_a09_0150_daigo_kill_shindo",
  "251": "auth_a10_0010_date_search_ir_sung_ha",
  "252": "auth_a10_0030_sayama_talk",
  "253": "auth_a10_0050_sayama_ask_bessho",
  "254": "auth_a10_0060_fight_with_chinpira",
  "255": "auth_a10_0080_kiryu_and_sayama_hide",
  "256": "auth_a10_0150_talk_with_sayama",
  "257": "auth_a11_0040_murai_kaisou",
  "258": "auth_a11_0060_knock_down_ir_sung_ha",
  "259": "auth_a12_0040_kazama_talk_ir_sung_boss",
  "260": "auth_a12_0050_kazama_go_away",
  "261": "auth_a12_0080_kiryu_was_stuck",
  "262": "auth_a12_0100_sengoku_kidnap_haruka",
  "263": "auth_a12_0160_get_back_haruka",
  "264": "auth_a13_0070_shoot_by_ir_sung_ha",
  "265": "auth_a13_0090_fight_with_kurahashi",
  "266": "auth_a13_0100_knock_down_kurahashi",
  "267": "auth_a13_0170_kawara_dead",
  "268": "auth_a14_0020_ryuuji_in_car",
  "269": "auth_a14_0050_kiryu_kiss_sayama",
  "270": "auth_a14_0090_toujoukai_preparation",
  "271": "auth_a14_0120_kiryu_help_yuuya",
  "272": "auth_a14_0130_kiryu_talk_ryuuji",
  "273": "auth_a15_0020_majima_cancel_bomb",
  "274": "auth_a15_0080_watch_sayama_vtr",
  "275": "auth_a16_0010_fight_with_ryuuji",
  "276": "auth_a16_0020_terada_arrival",
  "277": "auth_a16_0050_fight_with_ryuuji_again",
  "278": "auth_a16_0050_fight_with_ryuuji_again_a",
  "279": "auth_a16_0053_fight_with_ryuuji_again_b",
  "280": "auth_a16_0055_fight_with_ryuuji_again_c",
  "281": "auth_a16_0058_fight_with_ryuuji_again_d",
  "282": "auth_a17_0010_bomb_count_down",
  "283": "auth_a17_0020_epilogue",
  "284": "auth_c01_0070_kiryu_in_kamurocho",
  "285": "auth_c02_0043_tower_explosion",
  "286": "auth_c02_0046_kiryu_look_explosion",
  "287": "auth_c02_0050_kawara_look_explosion",
  "288": "auth_c02_0060_sudo_look_explosion",
  "289": "auth_c03_0030_kiryu_arrive_at_oumi",
  "290": "auth_c08_0060_kiryu_meet_hanaya_again",
  "291": "auth_c10_0090_play_in_doutonbori1",
  "292": "auth_c10_0100_play_in_takoyaki",
  "293": "auth_c10_0110_play_in_golf",
  "294": "auth_c10_0120_play_in_slot",
  "295": "auth_c10_0130_play_in_ufo_catcher",
  "296": "auth_c10_0140_play_in_doutonbori2",
  "297": "auth_c12_0070_kiryu_was_wet",
  "298": "auth_c12_0120_castle_split",
  "299": "auth_c13_0030_to_tower_1",
  "300": "auth_c13_0040_to_tower_2",
  "301": "auth_c13_0050_to_tower_3",
  "302": "auth_s02_0020_takashi_watch_monitor",
  "303": "speech_a01_0105_daigo",
  "304": "speech_a01_0105_kiryu",
  "305": "speech_c01_0018_boss",
  "306": "speech_c01_0018_kawara",
  "307": "speech_c01_0025_kashiwagi",
  "308": "speech_c01_0025_ryuji",
  "309": "speech_c01_0025_tsumura",
  "310": "speech_c01_0025_tsunematsu",
  "311": "speech_c01_0035_haruka",
  "312": "speech_c01_0035_kiryu",
  "313": "speech_c01_0035_oumi_hitman",
  "314": "speech_c01_0035_terada",
  "315": "speech_c01_0035_terada_buka",
  "316": "speech_c01_0035_yoshimura",
  "317": "speech_c01_0050_haruka",
  "318": "speech_c01_0050_kiryu",
  "319": "speech_c01_0050_rescue",
  "320": "speech_c01_0060_kanbua",
  "321": "speech_c01_0060_kanbub",
  "322": "speech_c01_0060_kanbuc",
  "323": "speech_c01_0060_kashiwagi",
  "324": "speech_c01_0060_kiryu",
  "325": "speech_c01_0060_toda",
  "326": "speech_c01_0060_yajima",
  "327": "speech_c01_0060_yayoi",
  "328": "speech_c01_0070_kiryu",
  "329": "speech_c01_0070_yayoi",
  "330": "speech_c01_0090_kiryu",
  "331": "speech_c01_0090_tasaka",
  "332": "speech_c01_0100_daigo",
  "333": "speech_c01_0100_kiryu",
  "334": "speech_c01_0100_tasaka",
  "335": "speech_c01_0110_kiryu",
  "336": "speech_c01_0120_daigo",
  "337": "speech_c01_0120_kiryu",
  "338": "speech_c02_0010_daigo",
  "339": "speech_c02_0010_kiryu",
  "340": "speech_c02_0043_announcer",
  "341": "speech_c02_0043_kiryu",
  "342": "speech_c02_0050_kawara",
  "343": "speech_c02_0060_sudo",
  "344": "speech_c03_0020_bessho",
  "345": "speech_c03_0020_kaoru",
  "346": "speech_c03_0020_sudo",
  "347": "speech_c03_0030_daigo",
  "348": "speech_c03_0030_kiryu",
  "349": "speech_c03_0030_oumi_a",
  "350": "speech_c03_0030_oumi_kumiin",
  "351": "speech_c03_0040_daigo",
  "352": "speech_c03_0040_jin",
  "353": "speech_c03_0040_kiryu",
  "354": "speech_c03_0040_sengoku",
  "355": "speech_c03_0040_takashima",
  "356": "speech_c03_0060_daigo",
  "357": "speech_c03_0060_kiryu",
  "358": "speech_c03_0060_ryuji",
  "359": "speech_c03_0070_daigo",
  "360": "speech_c03_0070_jin",
  "361": "speech_c03_0070_kiryu",
  "362": "speech_c03_0070_ryuji",
  "363": "speech_c04_0010_date",
  "364": "speech_c04_0010_kawara",
  "365": "speech_c04_0010_takako",
  "366": "speech_c04_0015_date",
  "367": "speech_c04_0015_kawara",
  "368": "speech_c04_0020_date",
  "369": "speech_c04_0020_kawara",
  "370": "speech_c04_0020_kurahashi",
  "371": "speech_c04_0020_ryuji",
  "372": "speech_c04_0020_sudo",
  "373": "speech_c04_0020_tsumura",
  "374": "speech_c04_0040_kiryu",
  "375": "speech_c04_0040_tamiyo",
  "376": "speech_c04_0050_kaoru",
  "377": "speech_c04_0050_kiryu",
  "378": "speech_c04_0050_tamiyo",
  "379": "speech_c04_0060_ezaki",
  "380": "speech_c04_0060_kiryu",
  "381": "speech_c04_0060_takashima",
  "382": "speech_c04_0070_bessho",
  "383": "speech_c04_0070_maruyama",
  "384": "speech_c04_0070_takashima",
  "385": "speech_c04_0080_ezaki",
  "386": "speech_c04_0080_kiryu",
  "387": "speech_c04_0110_kunieda",
  "388": "speech_c04_0110_sengoku",
  "389": "speech_c04_0120_bessho",
  "390": "speech_c04_0120_kaoru",
  "391": "speech_c04_0120_kiryu",
  "392": "speech_c04_0120_tamiyo",
  "393": "speech_c05_0030_kashiwagi",
  "394": "speech_c05_0030_kiryu",
  "395": "speech_c05_0030_shindou",
  "396": "speech_c05_0030_yayoi",
  "397": "speech_c05_0050_kaoru",
  "398": "speech_c05_0050_kiryu",
  "399": "speech_c05_0060_gaely",
  "400": "speech_c05_0060_kaoru",
  "401": "speech_c05_0060_kiryu",
  "402": "speech_c05_0070_kaoru",
  "403": "speech_c05_0070_kiryu",
  "404": "speech_c05_0080_kaoru",
  "405": "speech_c05_0080_kiryu",
  "406": "speech_c05_0080_majima",
  "407": "speech_c05_0090_ring_ana",
  "408": "speech_c05_0100_gaely",
  "409": "speech_c05_0100_kiryu",
  "410": "speech_c05_0100_ring_ana",
  "411": "speech_c05_0120_kiryu",
  "412": "speech_c05_0120_majima",
  "413": "speech_c05_0130_kiryu",
  "414": "speech_c05_0130_majima",
  "415": "speech_c07_0020_date",
  "416": "speech_c07_0020_kiryu",
  "417": "speech_c07_0020_master",
  "418": "speech_c07_0070_date",
  "419": "speech_c07_0070_drinkman",
  "420": "speech_c07_0070_kaoru",
  "421": "speech_c07_0070_kawara",
  "422": "speech_c07_0070_kiryu",
  "423": "speech_c07_0070_master",
  "424": "speech_c07_0080_kiryu",
  "425": "speech_c07_0080_master",
  "426": "speech_c07_0090_date",
  "427": "speech_c07_0090_kaoru",
  "428": "speech_c07_0090_kawara",
  "429": "speech_c07_0090_kiryu",
  "430": "speech_c08_0010_kijima",
  "431": "speech_c08_0010_kurahashi",
  "432": "speech_c08_0010_sudo",
  "433": "speech_c08_0030_date",
  "434": "speech_c08_0030_kaoru",
  "435": "speech_c08_0030_kawara",
  "436": "speech_c08_0030_kiryu",
  "437": "speech_c08_0040_kaoru",
  "438": "speech_c08_0040_kiryu",
  "439": "speech_c08_0060_hanaya",
  "440": "speech_c08_0060_kanazawa",
  "441": "speech_c08_0060_kaoru",
  "442": "speech_c08_0060_kiryu",
  "443": "speech_c08_0110_hayashi",
  "444": "speech_c08_0110_kaoru",
  "445": "speech_c08_0110_kiryu",
  "446": "speech_c08_0120_hayashi",
  "447": "speech_c08_0120_kaoru",
  "448": "speech_c08_0120_kiryu",
  "449": "speech_c08_0150_kaoru",
  "450": "speech_c08_0150_kiryu",
  "451": "speech_c08_0160_daigo",
  "452": "speech_c08_0160_kiryu",
  "453": "speech_c08_0170_daigo",
  "454": "speech_c08_0170_kiryu",
  "455": "speech_c09_0010_daigo",
  "456": "speech_c09_0010_kaoru",
  "457": "speech_c09_0010_kashiwagi",
  "458": "speech_c09_0010_kiryu",
  "459": "speech_c09_0030_daigo",
  "460": "speech_c09_0030_kaoru",
  "461": "speech_c09_0030_kashiwagi",
  "462": "speech_c09_0030_kiryu",
  "463": "speech_c09_0040_daigo",
  "464": "speech_c09_0040_kiryu",
  "465": "speech_c09_0040_outa",
  "466": "speech_c09_0040_outb",
  "467": "speech_c09_0040_yayoi",
  "468": "speech_c09_0050_daigo",
  "469": "speech_c09_0050_hashimoto",
  "470": "speech_c09_0050_kiryu",
  "471": "speech_c09_0080_sengokukumi",
  "472": "speech_c09_0100_kiryu",
  "473": "speech_c09_0100_shindou",
  "474": "speech_c09_0100_yayoi",
  "475": "speech_c09_0110_shindou",
  "476": "speech_c09_0110_toda",
  "477": "speech_c09_0110_todabuka",
  "478": "speech_c10_0020_date",
  "479": "speech_c10_0020_kaoru",
  "480": "speech_c10_0020_kiryu",
  "481": "speech_c10_0070_kaoru",
  "482": "speech_c10_0090_kaoru",
  "483": "speech_c10_0090_shopman",
  "484": "speech_c110_010_kaoru",
  "485": "speech_c110_010_kiryu",
  "486": "speech_c110_020_kaoru",
  "487": "speech_c110_020_kiryu",
  "488": "speech_c110_030_kaoru",
  "489": "speech_c110_030_keima",
  "490": "speech_c110_030_kiryu",
  "491": "speech_c110_030_murai",
  "492": "speech_c110_050_iruson",
  "493": "speech_c110_050_kaoru",
  "494": "speech_c110_050_keima",
  "495": "speech_c110_050_kiryu",
  "496": "speech_c110_050_murai",
  "497": "speech_c120_010_kiryu",
  "498": "speech_c120_020_kazama",
  "499": "speech_c120_020_kiryu",
  "500": "speech_c120_020_kiryu14",
  "501": "speech_c120_030_kiryu",
  "502": "speech_c120_060_kaoru",
  "503": "speech_c120_060_kiryu",
  "504": "speech_c120_090_tamiyo",
  "505": "speech_c120_110_kiryu",
  "506": "speech_c120_110_tamiyo",
  "507": "speech_c120_130_kiryu",
  "508": "speech_c120_130_kunieda",
  "509": "speech_c120_140_haruka",
  "510": "speech_c120_140_kiryu",
  "511": "speech_c120_140_sengoku",
  "512": "speech_c120_150_kiryu",
  "513": "speech_c120_150_sengoku",
  "514": "speech_c13_0010_haruka",
  "515": "speech_c13_0010_kaoru",
  "516": "speech_c13_0010_kiryu",
  "517": "speech_c13_0020_kaoru",
  "518": "speech_c13_0020_kiryu",
  "519": "speech_c13_0020_kurahashi",
  "520": "speech_c13_0030_bessho",
  "521": "speech_c13_0030_kawara",
  "522": "speech_c13_0030_tamiyo",
  "523": "speech_c13_0080_haruka",
  "524": "speech_c13_0080_kaoru",
  "525": "speech_c13_0080_kiryu",
  "526": "speech_c13_0120_kawara",
  "527": "speech_c13_0130_date",
  "528": "speech_c13_0130_kaoru",
  "529": "speech_c13_0130_kawara",
  "530": "speech_c13_0140_kawara",
  "531": "speech_c13_0140_suyoun",
  "532": "speech_c13_0150_date",
  "533": "speech_c13_0150_kaoru",
  "534": "speech_c13_0150_kawara",
  "535": "speech_c13_0150_tamiyo",
  "536": "speech_c13_0160_tamiyo",
  "537": "speech_c14_0010_date",
  "538": "speech_c14_0010_hanaya",
  "539": "speech_c14_0010_kaoru",
  "540": "speech_c14_0010_kiryu",
  "541": "speech_c14_0010_tamiyo",
  "542": "speech_c14_0030_maruyama",
  "543": "speech_c14_0030_takashima",
  "544": "speech_c14_0030_terada",
  "545": "speech_c14_0040_date",
  "546": "speech_c14_0040_hanaya",
  "547": "speech_c14_0040_kaoru",
  "548": "speech_c14_0060_date",
  "549": "speech_c14_0060_emoto",
  "550": "speech_c14_0060_kazuki",
  "551": "speech_c14_0060_kiryu",
  "552": "speech_c14_0060_yuuya",
  "553": "speech_c14_0070_daigo",
  "554": "speech_c14_0070_kashiwagi",
  "555": "speech_c14_0070_kiryu",
  "556": "speech_c14_0070_yayoi",
  "557": "speech_c14_0100_daigo",
  "558": "speech_c14_0100_date",
  "559": "speech_c14_0100_hanaya",
  "560": "speech_c14_0100_kiryu",
  "561": "speech_c14_0100_majima",
  "562": "speech_c14_0110_daigo",
  "563": "speech_c14_0110_hanaya",
  "564": "speech_c14_0110_kiryu",
  "565": "speech_c14_0110_majima",
  "566": "speech_c14_0110_master",
  "567": "speech_c14_0110_yuuya",
  "568": "speech_c15_0010_daigo",
  "569": "speech_c15_0010_kiryu",
  "570": "speech_c15_0010_yuuya",
  "571": "speech_c15_0040_kaoru",
  "572": "speech_c15_0050_date",
  "573": "speech_c15_0050_kiryu",
  "574": "speech_c15_0050_majima",
  "575": "speech_c15_0050_nishida",
  "576": "speech_c15_0060_date",
  "577": "speech_c15_0060_haruka",
  "578": "speech_c15_0060_kaoru",
  "579": "speech_c15_0060_kiryu",
  "580": "speech_c15_0060_sudo",
  "581": "speech_c15_0070_date",
  "582": "speech_c15_0070_kiryu",
  "583": "speech_c16_0030_dejin",
  "584": "speech_c16_0030_kazama",
  "585": "speech_c16_0030_kou",
  "586": "speech_c16_0030_shimano",
  "587": "speech_c16_0030_yonmin",
  "588": "speech_c16_0040_jin",
  "589": "speech_c16_0040_kiryu",
  "590": "speech_c16_0040_terada",
  "591": "speech_minig_darts_rival02",
  "592": "speech_minig_darts_rival03",
  "593": "speech_minig_karaokestaff",
  "594": "speech_minig_kiryu",
  "595": "speech_minig_mj_kindai_mid",
  "596": "speech_minig_mj_kindai_staff",
  "597": "speech_minig_mj_kindai_strong",
  "598": "speech_minig_mj_rarabai_mid",
  "599": "speech_minig_mj_rarabai_staff",
  "600": "speech_minig_mj_rarabai_weak",
  "601": "speech_s01_0010_s01_kouji",
  "602": "speech_s01_0010_s01_yuuya",
  "603": "speech_s01_0020_s01_kiryu",
  "604": "speech_s01_0020_s01_kouji",
  "605": "speech_s01_0020_s01_yuuya",
  "606": "speech_s01_0030_s01_okano",
  "607": "speech_s01_0030_s01_yuuya",
  "608": "speech_s02_0010_s02_kiryu",
  "609": "speech_s02_0010_s02_lady",
  "610": "speech_s02_0010_s02_takashi",
  "611": "speech_s02_0060_s02_atobe",
  "612": "speech_s02_0060_s02_kyouka",
  "613": "speech_s03_0010_s03_haruka",
  "614": "speech_s03_0010_s03_kiryu",
  "615": "speech_s03_0010_s03_sakura",
  "616": "speech_s03_0010_s03_shacho",
  "617": "speech_s03_0020_s03_haruka",
  "618": "speech_s03_0020_s03_kiryu",
  "619": "speech_s03_0020_s03_shacho",
  "620": "speech_s05_010_s05_kiryu",
  "621": "speech_s05_010_s05_machiko",
  "622": "speech_s05_020_s05_kiryu",
  "623": "speech_s05_020_s05_kumicho",
  "624": "speech_s05_020_s05_kumiin",
  "625": "speech_s05_020_s05_mama",
  "626": "speech_s05_030_s05_kiryu",
  "627": "speech_s06_0010_s06_douryou",
  "628": "speech_s06_0010_s06_kiryu",
  "629": "speech_s06_0010_s06_lady",
  "630": "speech_s06_0010_s06_wakamono",
  "631": "speech_s06_0020_s06_akimoto",
  "632": "speech_s06_0020_s06_haruka",
  "633": "speech_s06_0020_s06_kiryu",
  "634": "speech_s06_0020_s06_mizuki",
  "635": "speech_s08_0010_s08_kazebori",
  "636": "speech_s08_0010_s08_kiryu",
  "637": "speech_s08_0020b_s08_kazebori",
  "638": "speech_s08_0020b_s08_kiryu",
  "639": "speech_s08_0020c_s08_akina",
  "640": "speech_s08_0020c_s08_kazebori",
  "641": "speech_s08_0020_s08_akina",
  "642": "speech_s08_0020_s08_kazebori",
  "643": "speech_s08_0020_s08_kiryu",
  "644": "speech_s08_0030_s08_akina",
  "645": "speech_s08_0030_s08_kazebori",
  "646": "speech_s08_0030_s08_kiryu",
  "647": "speech_s08_0030_s08_satoshi",
  "648": "speech_s10_010_s10_kusogaki1",
  "649": "speech_s10_010_s10_kusogaki2",
  "650": "speech_s10_010_s10_nisekiryu",
  "651": "speech_s10_010_s10_niseshinji",
  "652": "speech_s10_020_s10_kiryu",
  "653": "speech_s10_020_s10_nisekiryu",
  "654": "speech_s10_020_s10_niseshinji",
  "655": "speech_shop_cmn_donkicrew",
  "656": "speech_shop_cmn_ebisuya",
  "657": "speech_shop_cmn_hsm_f_obasan",
  "658": "speech_shop_cmn_hsm_m_uncle",
  "659": "speech_shop_cmn_hsm_m_young_vita",
  "660": "speech_shop_cmn_knt_f_obasan",
  "661": "speech_shop_cmn_knt_f_young_mild",
  "662": "speech_shop_cmn_knt_f_young_nrm",
  "663": "speech_shop_cmn_knt_f_young_vita",
  "664": "speech_shop_cmn_knt_m_old",
  "665": "speech_shop_cmn_knt_m_uncle",
  "666": "speech_shop_cmn_knt_m_young_mild",
  "667": "speech_shop_cmn_knt_m_young_nrm",
  "668": "speech_shop_cmn_knt_m_young_vita",
  "669": "speech_shop_cmn_master",
  "670": "speech_shop_cmn_osk_m_young_mild",
  "671": "speech_shop_cmn_shop_eastan01",
  "672": "speech_shop_cmn_shop_westan01",
  "673": "speech_shop_cmn_sushigincrew",
  "674": "speech_shop_cmn_westan_m_nrm",
  "675": "speech_taxi_cmn_kamurotaxi01",
  "676": "speech_taxi_cmn_kamurotaxi02",
  "677": "speech_taxi_cmn_kiryu",
  "678": "battle_se_akiyama",
  "679": "battle_se_amon",
  "680": "battle_se_andou",
  "681": "battle_se_chan",
  "682": "battle_se_chn_m_big_tough",
  "683": "battle_se_chn_m_chinpira_nrm",
  "684": "battle_se_chn_m_chinpira_weak",
  "685": "battle_se_chn_m_nrm",
  "686": "battle_se_chn_m_yakuza_nrm",
  "687": "battle_se_chn_m_yakuza_tough",
  "688": "battle_se_daigo",
  "689": "battle_se_default",
  "690": "battle_se_eastan_m_nrm",
  "691": "battle_se_edo",
  "692": "battle_se_ghost01",
  "693": "battle_se_ghost02",
  "694": "battle_se_ghost03",
  "695": "battle_se_han",
  "696": "battle_se_hayashi",
  "697": "battle_se_hirose",
  "698": "battle_se_hsm_m_big_nrm",
  "699": "battle_se_hsm_m_big_tough",
  "700": "battle_se_hsm_m_chinpira_nrm",
  "701": "battle_se_hsm_m_chinpira_tough",
  "702": "battle_se_hsm_m_chinpira_weak",
  "703": "battle_se_hsm_m_uncle",
  "704": "battle_se_hsm_m_yakuza_inteli",
  "705": "battle_se_hsm_m_yakuza_nrm",
  "706": "battle_se_hsm_m_yakuza_warlike",
  "707": "battle_se_hsm_m_young_mild",
  "708": "battle_se_hsm_m_young_nrm",
  "709": "battle_se_hsm_m_young_vita",
  "710": "battle_se_jnk_m_downer",
  "711": "battle_se_jnk_m_sick",
  "712": "battle_se_jnk_m_upper",
  "713": "battle_se_joe",
  "714": "battle_se_kanamizawa",
  "715": "battle_se_kaneko",
  "716": "battle_se_kinniku",
  "717": "battle_se_kiryu",
  "718": "battle_se_knt_m_big_nrm",
  "719": "battle_se_knt_m_big_tough",
  "720": "battle_se_knt_m_chinpira_nrm",
  "721": "battle_se_knt_m_chinpira_tough",
  "722": "battle_se_knt_m_chinpira_weak",
  "723": "battle_se_knt_m_okama",
  "724": "battle_se_knt_m_old",
  "725": "battle_se_knt_m_uncle",
  "726": "battle_se_knt_m_yakuza_inteli",
  "727": "battle_se_knt_m_yakuza_nrm",
  "728": "battle_se_knt_m_yakuza_warlike",
  "729": "battle_se_knt_m_young_mild",
  "730": "battle_se_knt_m_young_nrm",
  "731": "battle_se_knt_m_young_vita",
  "732": "battle_se_kojima",
  "733": "battle_se_korean_m_nrm",
  "734": "battle_se_korean_m_tough",
  "735": "battle_se_korean_m_weak",
  "736": "battle_se_kosimizu",
  "737": "battle_se_koumei",
  "738": "battle_se_majima",
  "739": "battle_se_masao",
  "740": "battle_se_master",
  "741": "battle_se_masuzoe",
  "742": "battle_se_matunaga",
  "743": "battle_se_moritsuka",
  "744": "battle_se_nagumo",
  "745": "battle_se_naitou",
  "746": "battle_se_nisetaichi",
  "747": "battle_se_okada",
  "748": "battle_se_onoboss",
  "749": "battle_se_osk_m_big_nrm",
  "750": "battle_se_osk_m_big_tough",
  "751": "battle_se_osk_m_chinpira_nrm",
  "752": "battle_se_osk_m_chinpira_tough",
  "753": "battle_se_osk_m_chinpira_weak",
  "754": "battle_se_osk_m_uncle",
  "755": "battle_se_osk_m_yakuza_inteli",
  "756": "battle_se_osk_m_yakuza_nrm",
  "757": "battle_se_osk_m_yakuza_warlike",
  "758": "battle_se_osk_m_young_mild",
  "759": "battle_se_osk_m_young_nrm",
  "760": "battle_se_osk_m_young_vita",
  "761": "battle_se_pokecir",
  "762": "battle_se_ryuji",
  "763": "battle_se_saejima",
  "764": "battle_se_saigou",
  "765": "battle_se_satsuki",
  "766": "battle_se_sodachi",
  "767": "battle_se_someya",
  "768": "battle_se_tagasira",
  "769": "battle_se_tanahashi",
  "770": "battle_se_tenzan",
  "771": "battle_se_tsutsui",
  "772": "battle_se_tuneo",
  "773": "battle_se_westan_m_nrm",
  "774": "battle_se_westan_m_tough",
  "775": "battle_se_yano",
  "776": "battle_se_yuta",
  "777": "battle_se_zako",
  "778": "auth_shop",
  "779": "gv_buddy_chn_m_big_tough",
  "780": "gv_buddy_chn_m_chinpira_weak",
  "781": "gv_buddy_chn_m_yakuza_nrm",
  "782": "gv_buddy_chn_m_yakuza_tough",
  "783": "gv_buddy_default",
  "784": "gv_buddy_haruka",
  "785": "gv_buddy_kiryu",
  "786": "gv_buddy_knt_f_young_nrm",
  "787": "gv_buddy_knt_m_big_nrm",
  "788": "gv_buddy_knt_m_big_tough",
  "789": "gv_buddy_knt_m_chinpira_nrm",
  "790": "gv_buddy_knt_m_chinpira_tough",
  "791": "gv_buddy_knt_m_chinpira_weak",
  "792": "gv_buddy_knt_m_okama",
  "793": "gv_buddy_knt_m_uncle",
  "794": "gv_buddy_knt_m_yakuza_2nrm",
  "795": "gv_buddy_knt_m_yakuza_inteli",
  "796": "gv_buddy_knt_m_yakuza_nrm",
  "797": "gv_buddy_knt_m_yakuza_warlike",
  "798": "gv_buddy_knt_m_young_mild",
  "799": "gv_buddy_knt_m_young_nrm",
  "800": "gv_buddy_knt_m_young_vita",
  "801": "gv_buddy_osk_m_chinpira_weak",
  "802": "gv_buddy_osk_m_uncle",
  "803": "gv_buddy_osk_m_yakuza_nrm",
  "804": "gv_buddy_osk_m_young_mild",
  "805": "gv_buddy_westan_m_nrm",
  "806": "gv_chase_chn_m_big_tough",
  "807": "gv_chase_chn_m_chinpira_nrm",
  "808": "gv_chase_chn_m_chinpira_weak",
  "809": "gv_chase_chn_m_yakuza_nrm",
  "810": "gv_chase_chn_m_yakuza_tough",
  "811": "gv_chase_default",
  "812": "gv_chase_eastan_m_nrm",
  "813": "gv_chase_kiryu",
  "814": "gv_chase_knt_m_big_nrm",
  "815": "gv_chase_knt_m_big_tough",
  "816": "gv_chase_knt_m_chinpira_nrm",
  "817": "gv_chase_knt_m_chinpira_tough",
  "818": "gv_chase_knt_m_chinpira_weak",
  "819": "gv_chase_knt_m_okama",
  "820": "gv_chase_knt_m_old",
  "821": "gv_chase_knt_m_uncle",
  "822": "gv_chase_knt_m_yakuza_2nrm",
  "823": "gv_chase_knt_m_yakuza_inteli",
  "824": "gv_chase_knt_m_yakuza_nrm",
  "825": "gv_chase_knt_m_yakuza_warlike",
  "826": "gv_chase_knt_m_young_mild",
  "827": "gv_chase_knt_m_young_nrm",
  "828": "gv_chase_knt_m_young_vita",
  "829": "gv_chase_korean_m_nrm",
  "830": "gv_chase_korean_m_tough",
  "831": "gv_chase_korean_m_weak",
  "832": "gv_chase_osk_m_chinpira_weak",
  "833": "gv_chase_osk_m_uncle",
  "834": "gv_chase_osk_m_yakuza_nrm",
  "835": "gv_chase_osk_m_young_mild",
  "836": "gv_chase_westan_m_nrm",
  "837": "gv_cmn_chn_m_big_tough",
  "838": "gv_cmn_chn_m_chinpira_nrm",
  "839": "gv_cmn_chn_m_chinpira_weak",
  "840": "gv_cmn_chn_m_yakuza_nrm",
  "841": "gv_cmn_chn_m_yakuza_tough",
  "842": "gv_cmn_default",
  "843": "gv_cmn_eastan_f_nrm",
  "844": "gv_cmn_eastan_m_nrm",
  "845": "gv_cmn_haruka",
  "846": "gv_cmn_kiryu",
  "847": "gv_cmn_knt_f_child",
  "848": "gv_cmn_knt_f_obasan",
  "849": "gv_cmn_knt_f_old",
  "850": "gv_cmn_knt_f_sexy_20s",
  "851": "gv_cmn_knt_f_sexy_30s",
  "852": "gv_cmn_knt_f_young_mild",
  "853": "gv_cmn_knt_f_young_nrm",
  "854": "gv_cmn_knt_f_young_vita",
  "855": "gv_cmn_knt_m_big_nrm",
  "856": "gv_cmn_knt_m_big_tough",
  "857": "gv_cmn_knt_m_child",
  "858": "gv_cmn_knt_m_chinpira_nrm",
  "859": "gv_cmn_knt_m_chinpira_tough",
  "860": "gv_cmn_knt_m_chinpira_weak",
  "861": "gv_cmn_knt_m_okama",
  "862": "gv_cmn_knt_m_old",
  "863": "gv_cmn_knt_m_uncle",
  "864": "gv_cmn_knt_m_yakuza_2nrm",
  "865": "gv_cmn_knt_m_yakuza_inteli",
  "866": "gv_cmn_knt_m_yakuza_nrm",
  "867": "gv_cmn_knt_m_yakuza_warlike",
  "868": "gv_cmn_knt_m_young_mild",
  "869": "gv_cmn_knt_m_young_nrm",
  "870": "gv_cmn_knt_m_young_vita",
  "871": "gv_cmn_osk_f_sexy_20s",
  "872": "gv_cmn_osk_f_young_mild",
  "873": "gv_cmn_osk_f_young_nrm",
  "874": "gv_cmn_osk_f_young_vita",
  "875": "gv_cmn_osk_m_chinpira_weak",
  "876": "gv_cmn_osk_m_uncle",
  "877": "gv_cmn_osk_m_yakuza_nrm",
  "878": "gv_cmn_osk_m_young_mild",
  "879": "gv_cmn_westan_f_nrm",
  "880": "gv_cmn_westan_m_nrm",
  "881": "gv_enemy_chn_m_big_tough",
  "882": "gv_enemy_chn_m_chinpira_nrm",
  "883": "gv_enemy_chn_m_chinpira_weak",
  "884": "gv_enemy_chn_m_yakuza_nrm",
  "885": "gv_enemy_chn_m_yakuza_tough",
  "886": "gv_enemy_default",
  "887": "gv_enemy_eastan_m_nrm",
  "888": "gv_enemy_jnk_m_downer",
  "889": "gv_enemy_jnk_m_sick",
  "890": "gv_enemy_jnk_m_upper",
  "891": "gv_enemy_knt_m_big_nrm",
  "892": "gv_enemy_knt_m_big_tough",
  "893": "gv_enemy_knt_m_chinpira_nrm",
  "894": "gv_enemy_knt_m_chinpira_tough",
  "895": "gv_enemy_knt_m_chinpira_weak",
  "896": "gv_enemy_knt_m_okama",
  "897": "gv_enemy_knt_m_old",
  "898": "gv_enemy_knt_m_uncle",
  "899": "gv_enemy_knt_m_yakuza_2nrm",
  "900": "gv_enemy_knt_m_yakuza_inteli",
  "901": "gv_enemy_knt_m_yakuza_nrm",
  "902": "gv_enemy_knt_m_yakuza_warlike",
  "903": "gv_enemy_knt_m_young_mild",
  "904": "gv_enemy_knt_m_young_nrm",
  "905": "gv_enemy_knt_m_young_vita",
  "906": "gv_enemy_korean_m_nrm",
  "907": "gv_enemy_korean_m_tough",
  "908": "gv_enemy_korean_m_weak",
  "909": "gv_enemy_osk_m_chinpira_weak",
  "910": "gv_enemy_osk_m_uncle",
  "911": "gv_enemy_osk_m_yakuza_nrm",
  "912": "gv_enemy_osk_m_young_mild",
  "913": "gv_enemy_westan_m_nrm",
  "914": "gv_evenc_chn_m_big_tough",
  "915": "gv_evenc_chn_m_chinpira_nrm",
  "916": "gv_evenc_chn_m_chinpira_weak",
  "917": "gv_evenc_chn_m_yakuza_nrm",
  "918": "gv_evenc_chn_m_yakuza_tough",
  "919": "gv_evenc_default",
  "920": "gv_evenc_knt_m_big_nrm",
  "921": "gv_evenc_knt_m_big_tough",
  "922": "gv_evenc_knt_m_chinpira_nrm",
  "923": "gv_evenc_knt_m_chinpira_tough",
  "924": "gv_evenc_knt_m_chinpira_weak",
  "925": "gv_evenc_knt_m_yakuza_2nrm",
  "926": "gv_evenc_knt_m_yakuza_inteli",
  "927": "gv_evenc_knt_m_yakuza_nrm",
  "928": "gv_evenc_knt_m_yakuza_warlike",
  "929": "gv_evenc_knt_m_young_mild",
  "930": "gv_evenc_knt_m_young_nrm",
  "931": "gv_evenc_knt_m_young_vita",
  "932": "gv_evenc_osk_m_chinpira_weak",
  "933": "gv_evenc_osk_m_yakuza_nrm",
  "934": "gv_evenc_osk_m_young_mild",
  "935": "gv_fighter_chn_m_big_tough",
  "936": "gv_fighter_chn_m_chinpira_nrm",
  "937": "gv_fighter_chn_m_chinpira_weak",
  "938": "gv_fighter_chn_m_yakuza_nrm",
  "939": "gv_fighter_chn_m_yakuza_tough",
  "940": "gv_fighter_default",
  "941": "gv_fighter_eastan_m_nrm",
  "942": "gv_fighter_jnk_m_downer",
  "943": "gv_fighter_jnk_m_sick",
  "944": "gv_fighter_jnk_m_upper",
  "945": "gv_fighter_kiryu",
  "946": "gv_fighter_knt_m_big_nrm",
  "947": "gv_fighter_knt_m_big_tough",
  "948": "gv_fighter_knt_m_chinpira_nrm",
  "949": "gv_fighter_knt_m_chinpira_tough",
  "950": "gv_fighter_knt_m_chinpira_weak",
  "951": "gv_fighter_knt_m_okama",
  "952": "gv_fighter_knt_m_old",
  "953": "gv_fighter_knt_m_uncle",
  "954": "gv_fighter_knt_m_yakuza_2nrm",
  "955": "gv_fighter_knt_m_yakuza_inteli",
  "956": "gv_fighter_knt_m_yakuza_nrm",
  "957": "gv_fighter_knt_m_yakuza_warlike",
  "958": "gv_fighter_knt_m_young_mild",
  "959": "gv_fighter_knt_m_young_nrm",
  "960": "gv_fighter_knt_m_young_vita",
  "961": "gv_fighter_korean_m_nrm",
  "962": "gv_fighter_korean_m_tough",
  "963": "gv_fighter_korean_m_weak",
  "964": "gv_fighter_osk_m_chinpira_weak",
  "965": "gv_fighter_osk_m_uncle",
  "966": "gv_fighter_osk_m_yakuza_nrm",
  "967": "gv_fighter_osk_m_young_mild",
  "968": "gv_fighter_westan_m_nrm",
  "969": "gv_ichat_chn_m_big_tough",
  "970": "gv_ichat_chn_m_chinpira_nrm",
  "971": "gv_ichat_chn_m_chinpira_weak",
  "972": "gv_ichat_chn_m_yakuza_nrm",
  "973": "gv_ichat_chn_m_yakuza_tough",
  "974": "gv_ichat_default",
  "975": "gv_ichat_eastan_f_nrm",
  "976": "gv_ichat_knt_f_child",
  "977": "gv_ichat_knt_f_obasan",
  "978": "gv_ichat_knt_f_old",
  "979": "gv_ichat_knt_f_sexy_20s",
  "980": "gv_ichat_knt_f_sexy_30s",
  "981": "gv_ichat_knt_f_young_mild",
  "982": "gv_ichat_knt_f_young_nrm",
  "983": "gv_ichat_knt_f_young_vita",
  "984": "gv_ichat_knt_m_big_nrm",
  "985": "gv_ichat_knt_m_big_tough",
  "986": "gv_ichat_knt_m_child",
  "987": "gv_ichat_knt_m_chinpira_nrm",
  "988": "gv_ichat_knt_m_chinpira_tough",
  "989": "gv_ichat_knt_m_chinpira_weak",
  "990": "gv_ichat_knt_m_old",
  "991": "gv_ichat_knt_m_uncle",
  "992": "gv_ichat_knt_m_yakuza_2nrm",
  "993": "gv_ichat_knt_m_yakuza_inteli",
  "994": "gv_ichat_knt_m_yakuza_nrm",
  "995": "gv_ichat_knt_m_yakuza_warlike",
  "996": "gv_ichat_knt_m_young_mild",
  "997": "gv_ichat_knt_m_young_nrm",
  "998": "gv_ichat_knt_m_young_vita",
  "999": "gv_ichat_osk_f_sexy_20s",
  "1000": "gv_ichat_osk_f_young_mild",
  "1001": "gv_ichat_osk_f_young_nrm",
  "1002": "gv_ichat_osk_f_young_vita",
  "1003": "gv_ichat_osk_m_chinpira_weak",
  "1004": "gv_ichat_osk_m_uncle",
  "1005": "gv_ichat_osk_m_yakuza_nrm",
  "1006": "gv_ichat_osk_m_young_mild",
  "1007": "gv_igaya_chn_m_big_tough",
  "1008": "gv_igaya_chn_m_chinpira_nrm",
  "1009": "gv_igaya_chn_m_chinpira_weak",
  "1010": "gv_igaya_chn_m_yakuza_nrm",
  "1011": "gv_igaya_chn_m_yakuza_tough",
  "1012": "gv_igaya_default",
  "1013": "gv_igaya_eastan_f_nrm",
  "1014": "gv_igaya_knt_f_child",
  "1015": "gv_igaya_knt_f_obasan",
  "1016": "gv_igaya_knt_f_old",
  "1017": "gv_igaya_knt_f_sexy_20s",
  "1018": "gv_igaya_knt_f_sexy_30s",
  "1019": "gv_igaya_knt_f_young_mild",
  "1020": "gv_igaya_knt_f_young_nrm",
  "1021": "gv_igaya_knt_f_young_vita",
  "1022": "gv_igaya_knt_m_big_nrm",
  "1023": "gv_igaya_knt_m_big_tough",
  "1024": "gv_igaya_knt_m_child",
  "1025": "gv_igaya_knt_m_chinpira_nrm",
  "1026": "gv_igaya_knt_m_chinpira_tough",
  "1027": "gv_igaya_knt_m_chinpira_weak",
  "1028": "gv_igaya_knt_m_old",
  "1029": "gv_igaya_knt_m_uncle",
  "1030": "gv_igaya_knt_m_yakuza_2nrm",
  "1031": "gv_igaya_knt_m_yakuza_inteli",
  "1032": "gv_igaya_knt_m_yakuza_nrm",
  "1033": "gv_igaya_knt_m_yakuza_warlike",
  "1034": "gv_igaya_knt_m_young_mild",
  "1035": "gv_igaya_knt_m_young_nrm",
  "1036": "gv_igaya_knt_m_young_vita",
  "1037": "gv_igaya_osk_f_sexy_20s",
  "1038": "gv_igaya_osk_f_young_mild",
  "1039": "gv_igaya_osk_f_young_nrm",
  "1040": "gv_igaya_osk_f_young_vita",
  "1041": "gv_igaya_osk_m_chinpira_weak",
  "1042": "gv_igaya_osk_m_uncle",
  "1043": "gv_igaya_osk_m_yakuza_nrm",
  "1044": "gv_igaya_osk_m_young_mild",
  "1045": "gv_talk_chn_m_big_tough",
  "1046": "gv_talk_chn_m_chinpira_nrm",
  "1047": "gv_talk_chn_m_chinpira_weak",
  "1048": "gv_talk_chn_m_yakuza_nrm",
  "1049": "gv_talk_chn_m_yakuza_tough",
  "1050": "gv_talk_default",
  "1051": "gv_talk_eastan_f_nrm",
  "1052": "gv_talk_eastan_m_nrm",
  "1053": "gv_talk_haruka",
  "1054": "gv_talk_knt_f_child",
  "1055": "gv_talk_knt_f_obasan",
  "1056": "gv_talk_knt_f_old",
  "1057": "gv_talk_knt_f_sexy_20s",
  "1058": "gv_talk_knt_f_sexy_30s",
  "1059": "gv_talk_knt_f_young_mild",
  "1060": "gv_talk_knt_f_young_nrm",
  "1061": "gv_talk_knt_f_young_vita",
  "1062": "gv_talk_knt_m_big_nrm",
  "1063": "gv_talk_knt_m_big_tough",
  "1064": "gv_talk_knt_m_child",
  "1065": "gv_talk_knt_m_chinpira_nrm",
  "1066": "gv_talk_knt_m_chinpira_tough",
  "1067": "gv_talk_knt_m_chinpira_weak",
  "1068": "gv_talk_knt_m_okama",
  "1069": "gv_talk_knt_m_old",
  "1070": "gv_talk_knt_m_uncle",
  "1071": "gv_talk_knt_m_yakuza_2nrm",
  "1072": "gv_talk_knt_m_yakuza_inteli",
  "1073": "gv_talk_knt_m_yakuza_nrm",
  "1074": "gv_talk_knt_m_yakuza_warlike",
  "1075": "gv_talk_knt_m_young_mild",
  "1076": "gv_talk_knt_m_young_nrm",
  "1077": "gv_talk_knt_m_young_vita",
  "1078": "gv_talk_osk_f_sexy_20s",
  "1079": "gv_talk_osk_f_young_mild",
  "1080": "gv_talk_osk_f_young_nrm",
  "1081": "gv_talk_osk_f_young_vita",
  "1082": "gv_talk_osk_m_chinpira_weak",
  "1083": "gv_talk_osk_m_uncle",
  "1084": "gv_talk_osk_m_yakuza_nrm",
  "1085": "gv_talk_osk_m_young_mild",
  "1086": "gv_talk_westan_f_nrm",
  "1087": "gv_talk_westan_m_nrm",
  "1088": "gv_buddy_joe",
  "1089": "gv_buddy_kojima",
  "1090": "gv_buddy_koumei",
  "1091": "gv_buddy_masao",
  "1092": "gv_buddy_master",
  "1093": "gv_buddy_naitou",
  "1094": "gv_buddy_okada",
  "1095": "gv_buddy_onoboss",
  "1096": "gv_buddy_satsuki",
  "1097": "gv_buddy_tanahashi",
  "1098": "gv_buddy_tenzan",
  "1099": "gv_buddy_yano",
  "1100": "gv_cmn_joe",
  "1101": "gv_cmn_masao",
  "1102": "gv_cmn_master",
  "1103": "gv_cmn_sachiko",
  "1104": "gv_cmn_urashop",
  "1105": "gv_cmn_urashopkamu",
  "1106": "gv_enemy_joe",
  "1107": "gv_enemy_kojima",
  "1108": "gv_enemy_koumei",
  "1109": "gv_enemy_masao",
  "1110": "gv_enemy_master",
  "1111": "gv_enemy_naitou",
  "1112": "gv_enemy_okada",
  "1113": "gv_enemy_onoboss",
  "1114": "gv_enemy_satsuki",
  "1115": "gv_enemy_tanahashi",
  "1116": "gv_enemy_tenzan",
  "1117": "gv_enemy_yano",
  "1118": "gv_fighter_joe",
  "1119": "gv_fighter_kojima",
  "1120": "gv_fighter_koumei",
  "1121": "gv_fighter_masao",
  "1122": "gv_fighter_master",
  "1123": "gv_fighter_naitou",
  "1124": "gv_fighter_okada",
  "1125": "gv_fighter_onoboss",
  "1126": "gv_fighter_satsuki",
  "1127": "gv_fighter_tanahashi",
  "1128": "gv_fighter_tenzan",
  "1129": "gv_fighter_yano",
  "1130": "gv_talk_joe",
  "1131": "gv_talk_masao",
  "1132": "gv_talk_master",
  "1133": "gv_talk_urashop",
  "1134": "gv_talk_urashopkamu",
  "1135": "gv_cmn_cat01",
  "1136": "gv_cmn_cat02",
  "1137": "gv_cmn_cat03",
  "1138": "gv_cmn_cat04",
  "1139": "gv_cmn_cat05",
  "1140": "gv_buddy_akiyama",
  "1141": "gv_buddy_daigo",
  "1142": "gv_buddy_date",
  "1143": "gv_buddy_majima",
  "1144": "gv_buddy_saejima",
  "1145": "gv_cmn_akiyama",
  "1146": "gv_cmn_daigo",
  "1147": "gv_cmn_date",
  "1148": "gv_cmn_majima",
  "1149": "gv_enemy_akiyama",
  "1150": "gv_enemy_daigo",
  "1151": "gv_enemy_date",
  "1152": "gv_enemy_majima",
  "1153": "gv_enemy_saejima",
  "1154": "gv_fighter_akiyama",
  "1155": "gv_fighter_daigo",
  "1156": "gv_fighter_date",
  "1157": "gv_fighter_gaely",
  "1158": "gv_fighter_majima",
  "1159": "gv_fighter_ryuji",
  "1160": "gv_fighter_saejima",
  "1161": "gv_talk_akiyama",
  "1162": "gv_talk_daigo",
  "1163": "gv_talk_date",
  "1164": "gv_talk_majima",
  "1165": "gv_cmn_hayashi",
  "1166": "gv_cmn_kashiwagi",
  "1167": "gv_cmn_kazuki",
  "1168": "gv_cmn_shimano",
  "1169": "gv_cmn_sudo",
  "1170": "gv_cmn_terada",
  "1171": "gv_cmn_yuuya",
  "1172": "gv_fighter_hayashi",
  "1173": "gv_fighter_yuuya",
  "1174": "gv_talk_hayashi",
  "1175": "gv_talk_kashiwagi",
  "1176": "gv_talk_kazuki",
  "1177": "gv_talk_shimano",
  "1178": "gv_talk_sudo",
  "1179": "gv_talk_terada",
  "1180": "gv_talk_yuuya",
  "1181": "gv_talk_tamiyo",
  "1182": "gv_mng_bj_kiryu",
  "1183": "gv_mng_bj_mng_dealer",
  "1184": "gv_mng_common_kiryu",
  "1185": "gv_mng_koikoi_kiryu",
  "1186": "gv_mng_oicho_kiryu",
  "1187": "gv_mng_poker_kiryu",
  "1188": "gv_mng_poker_mng_dealer",
  "1189": "gv_mng_shogi_kiryu",
  "1190": "gv_mng_shogi_mng_shinpan",
  "1191": "gv_buddy_amon",
  "1192": "gv_buddy_ando",
  "1193": "gv_buddy_kanamizawa",
  "1194": "gv_buddy_kaneko",
  "1195": "gv_buddy_pokecir",
  "1196": "gv_buddy_saigou",
  "1197": "gv_buddy_sodachi",
  "1198": "gv_enemy_amon",
  "1199": "gv_enemy_ando",
  "1200": "gv_enemy_kanamizawa",
  "1201": "gv_enemy_kaneko",
  "1202": "gv_enemy_pokecir",
  "1203": "gv_enemy_saigou",
  "1204": "gv_enemy_sodachi",
  "1205": "gv_fighter_amon",
  "1206": "gv_fighter_ando",
  "1207": "gv_fighter_kanamizawa",
  "1208": "gv_fighter_kaneko",
  "1209": "gv_fighter_pokecir",
  "1210": "gv_fighter_saigou",
  "1211": "gv_fighter_sodachi",
  "1212": "hact_cln_a61420_clan_btlst",
  "1213": "hact_cln_a61430_clan_btl_win",
  "1214": "hact_cln_a61440_clan_btl_lose",
  "1215": "hact_h1500",
  "1216": "hact_h2000_knock_wall_l",
  "1217": "hact_h2011_wall_knock_neck",
  "1218": "hact_h2020_table90_lapel",
  "1219": "hact_h2030_table90_neck",
  "1220": "hact_h23040_mjm_keritobashi",
  "1221": "hact_h23580",
  "1222": "hact_h23590",
  "1223": "hact_h23600",
  "1224": "hact_h23610",
  "1225": "hact_h23670_kado_oi_hook",
  "1226": "hact_h23680_buki_a",
  "1227": "hact_h23680_buki_b",
  "1228": "hact_h23701_buki_f",
  "1229": "hact_h23710_buki_d",
  "1230": "hact_h23720_buki_e",
  "1231": "hact_h23721_buki_e_boku",
  "1232": "hact_h23740_buki_g",
  "1233": "hact_h23750_buki_h",
  "1234": "hact_h23760_buki_n",
  "1235": "hact_h23780_buki_y",
  "1236": "hact_h23790_pole_hit",
  "1237": "hact_h23820_buki_a_snatch",
  "1238": "hact_h23830_buki_b_snatch",
  "1239": "hact_h23840_buki_d_snatch",
  "1240": "hact_h23841_buki_bat_snatch",
  "1241": "hact_h23850_buki_e_snatch",
  "1242": "hact_h23860_buki_g_snatch",
  "1243": "hact_h23870_buki_y_snatch",
  "1244": "hact_h23880_23881_train_reaction",
  "1245": "hact_h23900_tag_hiza",
  "1246": "hact_h23910_tag_swing",
  "1247": "hact_h23940_jump_lariat",
  "1248": "hact_h24000_oi_motare",
  "1249": "hact_h24010_100punchi",
  "1250": "hact_h24020_100kick",
  "1251": "hact_h24030_sway_f",
  "1252": "hact_h24040_sway_b",
  "1253": "hact_h24050_sway_l",
  "1254": "hact_h24060_sway_r",
  "1255": "hact_h24070_headlock_nage",
  "1256": "hact_h24080_kubi_nage",
  "1257": "hact_h24090_oi_sobat",
  "1258": "hact_h24100_oi_dropkick",
  "1259": "hact_h24110_c_german",
  "1260": "hact_h24120_denshirenji",
  "1261": "hact_h24130_hizafumitsuke",
  "1262": "hact_h24140_kubimawashi",
  "1263": "hact_h24150_hashi",
  "1264": "hact_h24160_ukenagashi",
  "1265": "hact_h24170_charge_hi",
  "1266": "hact_h24190_nageotoshi_kubi",
  "1267": "hact_h24200_sexy_wanderer",
  "1268": "hact_h24210_saku_kubi",
  "1269": "hact_h24220_24230_makikomi_nage",
  "1270": "hact_h24240_guardbreak",
  "1271": "hact_h24520_edo1_tag_akiyama",
  "1272": "hact_h24530_edo1_akiyama_kick",
  "1273": "hact_h24550_akiyama_auth",
  "1274": "hact_h24560_akiyama_jumpkick",
  "1275": "hact_h24580_3_damage",
  "1276": "hact_h24590_xchop_nagumo",
  "1277": "hact_h24600_head_yuta",
  "1278": "hact_h24610_lariat_matsu",
  "1279": "hact_h24620_masu1_tag_lapel",
  "1280": "hact_h24630_masu1_tag_neck",
  "1281": "hact_h24650_yuta_taga_boss",
  "1282": "hact_h24660_yuta_taga_tag",
  "1283": "hact_h2651_grail_knock_f",
  "1284": "hact_manhole_move",
  "1285": "hact_sfx_m40001_reach",
  "1286": "hact_sfx_m40002_lon",
  "1287": "hact_sfx_m40003_tsumo",
  "1288": "hact_sfx_m40004_miss",
  "1289": "hact_sfx_m401000_darts_st_1p",
  "1290": "hact_sfx_m40110_darts_st_2p_m",
  "1291": "hact_sfx_m40120_darts_st_2p_f",
  "1292": "haichi_amb_aircon_out01",
  "1293": "haichi_amb_aircon_out02",
  "1294": "haichi_amb_aircon_out03",
  "1295": "haichi_amb_aircon_out04",
  "1296": "haichi_amb_aircon_out05",
  "1297": "haichi_amb_aircon_out06",
  "1298": "haichi_amb_aircon_out07",
  "1299": "haichi_amb_aircon_out08",
  "1300": "haichi_amb_car_street",
  "1301": "haichi_amb_construct",
  "1302": "haichi_amb_gesui_water01",
  "1303": "haichi_amb_gesui_water02",
  "1304": "haichi_amb_inside_kamuro",
  "1305": "haichi_amb_o_aircon_out01",
  "1306": "haichi_amb_o_inside_osaka",
  "1307": "haichi_amb_o_river",
  "1308": "haichi_amb_rooftoop_water_fall",
  "1309": "haichi_amb_rooftoop_water_lane",
  "1310": "haichi_amb_sai_river",
  "1311": "haichi_amb_siren",
  "1312": "haichi_amb_warai",
  "1313": "haichi_bgm_asian01",
  "1314": "haichi_bgm_asian02",
  "1315": "haichi_bgm_asian03",
  "1316": "haichi_bgm_caba_shine",
  "1317": "haichi_bgm_edm01",
  "1318": "haichi_bgm_edm02",
  "1319": "haichi_bgm_edm03",
  "1320": "haichi_bgm_edm04",
  "1321": "haichi_bgm_edm05",
  "1322": "haichi_bgm_edm06",
  "1323": "haichi_bgm_fuzoku01",
  "1324": "haichi_bgm_fuzoku02",
  "1325": "haichi_bgm_inside_fuzoku01",
  "1326": "haichi_bgm_inside_fuzoku02",
  "1327": "haichi_bgm_inside_karaoke01",
  "1328": "haichi_bgm_inside_karaoke02",
  "1329": "haichi_bgm_karaoke01",
  "1330": "haichi_bgm_karaoke02",
  "1331": "haichi_bgm_o_karaoke01",
  "1332": "haichi_bgm_o_xmas",
  "1333": "haichi_bgm_pachinko01",
  "1334": "haichi_bgm_pub01",
  "1335": "haichi_bgm_sai_koto",
  "1336": "haichi_bgm_sai_shamisen",
  "1337": "haichi_bgm_stardust",
  "1338": "haichi_bgm_usen_cafe",
  "1339": "haichi_bgm_usen_donki",
  "1340": "haichi_bgm_usen_karaoke01",
  "1341": "haichi_bgm_usen_karaoke02",
  "1342": "haichi_construct01",
  "1343": "haichi_construct02",
  "1344": "haichi_construct03",
  "1345": "haichi_construct04",
  "1346": "haichi_construct05",
  "1347": "haichi_construct06",
  "1348": "haichi_door_chime",
  "1349": "haichi_game",
  "1350": "haichi_gaya_k_pub01",
  "1351": "haichi_gaya_k_pub02",
  "1352": "haichi_gaya_k_pub03",
  "1353": "haichi_gaya_k_pub04",
  "1354": "haichi_pachinko01",
  "1355": "haichi_pachinko02",
  "1356": "haichi_song_jungleboy",
  "1357": "haichi_tape_karaoke_daitokai",
  "1358": "haichi_tape_police01",
  "1359": "haichi_tape_police02",
  "1360": "haichi_tape_police03",
  "1361": "battle_se_yagami",
  "1362": "act_player",
  "1363": "chase_stalking_common",
  "1364": "gv_chase_yagami",
  "1365": "gv_fighter_yagami",
  "1366": "gv_mng_bj_yagami",
  "1367": "gv_mng_common_yagami",
  "1368": "gv_mng_koikoi_yagami",
  "1369": "gv_mng_oicho_yagami",
  "1370": "gv_mng_poker_yagami",
  "1371": "gv_mng_shogi_yagami",
  "1372": "minig_batting_yagami",
  "1373": "minig_darts_yagami",
  "1374": "minig_mj_yagami",
  "1375": "hact_ja10000_kj_2f_encount",
  "1376": "hact_ja70000_hact_police_incoming",
  "1377": "hact_jh1510_oi_kickover_utu",
  "1378": "hact_jh1621_mount_c",
  "1379": "hact_jh1630_hact_oi_soul",
  "1380": "hact_jh2010_wall_knock_neck",
  "1381": "hact_jh2030_table90_neck",
  "1382": "hact_jh24080_kubi_nage",
  "1383": "hact_jh27210_air",
  "1384": "hact_jh27430_ex_sen",
  "1385": "hact_jh27440_ex_mai",
  "1386": "hact_jh5470_gao_kneekick",
  "1387": "detect_act_drone",
  "1388": "detect_act_unlock",
  "1389": "mng_drone_race",
  "1390": "talk_c01_020_judge_proto",
  "1391": "step_dash_barefoot",
  "1392": "step_dash_boots",
  "1393": "step_dash_leather",
  "1394": "step_dash_no_shoes",
  "1395": "step_dash_sneaker",
  "1396": "step_dash_spike",
  "1397": "step_run_barefoot",
  "1398": "step_run_boots",
  "1399": "step_run_leather",
  "1400": "step_run_no_shoes",
  "1401": "step_run_sneaker",
  "1402": "step_run_spike",
  "1403": "step_walk_barefoot",
  "1404": "step_walk_boots",
  "1405": "step_walk_leather",
  "1406": "step_walk_no_shoes",
  "1407": "step_walk_sneaker",
  "1408": "step_walk_spike",
  "1409": "step_wdrwalk",
  "1410": "talk_c01_0018",
  "1411": "talk_c01_0025",
  "1412": "talk_c01_0035",
  "1413": "talk_c01_0050",
  "1414": "talk_c01_0060",
  "1415": "talk_c01_0090",
  "1416": "talk_c01_0110",
  "1417": "talk_c01_0120",
  "1418": "talk_c02_0010",
  "1419": "talk_c03_0020",
  "1420": "talk_c03_0040",
  "1421": "talk_c03_0060",
  "1422": "talk_c03_0070",
  "1423": "talk_c04_0010",
  "1424": "talk_c04_0015",
  "1425": "talk_c04_0020",
  "1426": "talk_c04_0040",
  "1427": "talk_c04_0050",
  "1428": "talk_c04_0060",
  "1429": "talk_c04_0070",
  "1430": "talk_c04_0080",
  "1431": "talk_c04_0110",
  "1432": "talk_c04_0120",
  "1433": "talk_c05_0030",
  "1434": "talk_c05_0050",
  "1435": "talk_c05_0060",
  "1436": "talk_c05_0070",
  "1437": "talk_c05_0080",
  "1438": "talk_c05_0090",
  "1439": "talk_c05_0100",
  "1440": "talk_c05_0120",
  "1441": "talk_c05_0130",
  "1442": "talk_c07_0020",
  "1443": "talk_c07_0080",
  "1444": "talk_c07_0090",
  "1445": "talk_c08_0030",
  "1446": "talk_c08_0040",
  "1447": "talk_c08_0050",
  "1448": "talk_c08_0100",
  "1449": "talk_c08_0110",
  "1450": "talk_c08_0120",
  "1451": "talk_c08_0160",
  "1452": "talk_c08_0170",
  "1453": "talk_c09_0040",
  "1454": "talk_c09_0100",
  "1455": "talk_c10_0070",
  "1456": "talk_c12_0060",
  "1457": "talk_c14_0030",
  "1458": "talk_c14_0060",
  "1459": "talk_c14_0070",
  "1460": "talk_c16_0040",
  "1461": "talk_s02_0010",
  "1462": "talk_s03_0010",
  "1463": "talk_s03_0020",
  "1464": "talk_s08_0010",
  "1465": "talk_s08_0020",
  "1466": "talk_s08_0030",
  "1467": "talk_food_cmn",
  "1468": "talk_telecom_cmn",
  "1469": "talk_s01_0010",
  "1470": "talk_s01_0020",
  "1471": "talk_s01_0030",
  "1472": "talk_s05_0010",
  "1473": "talk_s05_0020",
  "1474": "talk_s06_0010",
  "1475": "talk_s06_0020",
  "1476": "talk_s10_0010",
  "1477": "talk_s10_0020",
  "1478": "talk_sub_common",
  "1479": "auth_lip_check"
}